cmsgpack/__init__.py
cmsgpack/cmsgpack.cpython-312-x86_64-linux-musl.so
cmsgpack/cmsgpack.pyi
cmsgpack-0.1.2.dist-info/LICENSE
cmsgpack-0.1.2.dist-info/METADATA
cmsgpack-0.1.2.dist-info/WHEEL
cmsgpack-0.1.2.dist-info/RECORD
