Metadata-Version: 2.1
Name: cmsgpack
Version: 0.1.2
Summary: Fast MessagePack serializer for Python
Author-Email: Sven Boertjens <boertjens.sven@gmail.com>
License: Copyright 2025 Sven Boertjens
Project-URL: Homepage, https://github.com/svenboertjens/cmsgpack
Requires-Python: >=3.12
